{
  "base": "PDX",
  "seat": "FO",
  "pilots": [
    {
      "seniority": 593,
      "name": "Shannan L. Hill",
      "rank": 1
    },
    {
      "seniority": 747,
      "name": "Kelly E. Knebel",
      "rank": 2
    },
    {
      "seniority": 785,
      "name": "Michael W. Myers",
      "rank": 3
    },
    {
      "seniority": 797,
      "name": "Beverly D. Terry",
      "rank": 4
    },
    {
      "seniority": 1073,
      "name": "Andrea M. Parker",
      "rank": 5
    },
    {
      "seniority": 1095,
      "name": "John Mergner",
      "rank": 6
    },
    {
      "seniority": 1155,
      "name": "Kali Harvey",
      "rank": 7
    },
    {
      "seniority": 1208,
      "name": "Harlan Jackson",
      "rank": 8
    },
    {
      "seniority": 1299,
      "name": "Erika McAlister",
      "rank": 9
    },
    {
      "seniority": 1344,
      "name": "Erik Niederman",
      "rank": 10
    },
    {
      "seniority": 1369,
      "name": "Renee Hershberger",
      "rank": 11
    },
    {
      "seniority": 1375,
      "name": "Justin Weier",
      "rank": 12
    },
    {
      "seniority": 1376,
      "name": "Janae Greer",
      "rank": 13
    },
    {
      "seniority": 1415,
      "name": "Jeff Hwang",
      "rank": 14
    },
    {
      "seniority": 1420,
      "name": "Michael D. Geiger",
      "rank": 15
    },
    {
      "seniority": 1433,
      "name": "Duncan Roberts",
      "rank": 16
    },
    {
      "seniority": 1438,
      "name": "Caitlin Chenoweth",
      "rank": 17
    },
    {
      "seniority": 1531,
      "name": "Casey Hughes",
      "rank": 18
    },
    {
      "seniority": 1567,
      "name": "Tye Brown",
      "rank": 19
    },
    {
      "seniority": 1579,
      "name": "Joshua Stahly",
      "rank": 20
    },
    {
      "seniority": 1595,
      "name": "Katrina Horobiowski",
      "rank": 21
    },
    {
      "seniority": 1633,
      "name": "Lukus Levesque",
      "rank": 22
    },
    {
      "seniority": 1664,
      "name": "Jeromy Oelschlager",
      "rank": 23
    },
    {
      "seniority": 1696,
      "name": "Galen Godsil",
      "rank": 24
    },
    {
      "seniority": 1713,
      "name": "Thomas Grob",
      "rank": 25
    },
    {
      "seniority": 1754,
      "name": "Robert Mitchell",
      "rank": 26
    },
    {
      "seniority": 1756,
      "name": "Joshua Hanson",
      "rank": 27
    },
    {
      "seniority": 1761,
      "name": "Andrew Hart",
      "rank": 28
    },
    {
      "seniority": 1767,
      "name": "Thomas Norin",
      "rank": 29
    },
    {
      "seniority": 1777,
      "name": "Tobias Ensele",
      "rank": 30
    },
    {
      "seniority": 1778,
      "name": "Nicholas Burik",
      "rank": 31
    },
    {
      "seniority": 1800,
      "name": "David Bruton",
      "rank": 32
    },
    {
      "seniority": 1835,
      "name": "Mark Holden",
      "rank": 33
    },
    {
      "seniority": 1843,
      "name": "Jack Bylsma",
      "rank": 34
    },
    {
      "seniority": 1854,
      "name": "Spencer Howard",
      "rank": 35
    },
    {
      "seniority": 1855,
      "name": "Jason Carr",
      "rank": 36
    },
    {
      "seniority": 1874,
      "name": "Justin Brandt",
      "rank": 37
    },
    {
      "seniority": 1899,
      "name": "Justin Saxe",
      "rank": 38
    },
    {
      "seniority": 1904,
      "name": "Charley Pruitt",
      "rank": 39
    },
    {
      "seniority": 1906,
      "name": "Charles Yonge",
      "rank": 40
    },
    {
      "seniority": 1907,
      "name": "Scott Ableidinger",
      "rank": 41
    },
    {
      "seniority": 1908,
      "name": "Mathew Dolan",
      "rank": 42
    },
    {
      "seniority": 1910,
      "name": "Tiffany Schuler",
      "rank": 43
    },
    {
      "seniority": 1915,
      "name": "Jeremy Nogowski",
      "rank": 44
    },
    {
      "seniority": 1923,
      "name": "Matt West",
      "rank": 45
    },
    {
      "seniority": 1925,
      "name": "Ryan Cox",
      "rank": 46
    },
    {
      "seniority": 1930,
      "name": "Val German",
      "rank": 47
    },
    {
      "seniority": 1932,
      "name": "Clint Chase",
      "rank": 48
    },
    {
      "seniority": 1941,
      "name": "Brian Unterseher",
      "rank": 49
    },
    {
      "seniority": 1946,
      "name": "Michael Schaper",
      "rank": 50
    },
    {
      "seniority": 1948,
      "name": "Kevin Melhorn",
      "rank": 51
    },
    {
      "seniority": 1957,
      "name": "Seth Olson",
      "rank": 52
    },
    {
      "seniority": 1989,
      "name": "Kristina Hubbard",
      "rank": 53
    },
    {
      "seniority": 1996,
      "name": "Steve Marean",
      "rank": 54
    },
    {
      "seniority": 2009,
      "name": "Cary Freeman",
      "rank": 55
    },
    {
      "seniority": 2011,
      "name": "Jonathan Flowers",
      "rank": 56
    },
    {
      "seniority": 2015,
      "name": "Emily Wiprud",
      "rank": 57
    },
    {
      "seniority": 2017,
      "name": "Trevor Conroy",
      "rank": 58
    },
    {
      "seniority": 2022,
      "name": "Michael Delavar",
      "rank": 59
    },
    {
      "seniority": 2028,
      "name": "Keith Lawson",
      "rank": 60
    },
    {
      "seniority": 2049,
      "name": "Scot Milani",
      "rank": 61
    },
    {
      "seniority": 2054,
      "name": "Brock Leinberger",
      "rank": 62
    },
    {
      "seniority": 2060,
      "name": "Brandon Drake",
      "rank": 63
    },
    {
      "seniority": 2061,
      "name": "Connor Frain",
      "rank": 64
    },
    {
      "seniority": 2076,
      "name": "Mark Skolnick",
      "rank": 65
    },
    {
      "seniority": 2104,
      "name": "Ian Shanahan",
      "rank": 66
    },
    {
      "seniority": 2106,
      "name": "Robert Davis",
      "rank": 67
    },
    {
      "seniority": 2117,
      "name": "Sara Gamblin",
      "rank": 68
    },
    {
      "seniority": 2135,
      "name": "John Sarigiannides",
      "rank": 69
    },
    {
      "seniority": 2141,
      "name": "Casey Rose",
      "rank": 70
    },
    {
      "seniority": 2154,
      "name": "David Roller",
      "rank": 71
    },
    {
      "seniority": 2155,
      "name": "John Rich",
      "rank": 72
    },
    {
      "seniority": 2156,
      "name": "Sara Zieske",
      "rank": 73
    },
    {
      "seniority": 2158,
      "name": "Chad Klinzing",
      "rank": 74
    },
    {
      "seniority": 2160,
      "name": "Jared Loveland",
      "rank": 75
    },
    {
      "seniority": 2162,
      "name": "Craig Sevigny",
      "rank": 76
    },
    {
      "seniority": 2166,
      "name": "James Ricketts",
      "rank": 77
    },
    {
      "seniority": 2178,
      "name": "Zachary Grice",
      "rank": 78
    },
    {
      "seniority": 2184,
      "name": "Jason Webberley",
      "rank": 79
    },
    {
      "seniority": 2185,
      "name": "Christopher Sandor",
      "rank": 80
    },
    {
      "seniority": 2191,
      "name": "Nick Harris",
      "rank": 81
    },
    {
      "seniority": 2199,
      "name": "Jodi Stahly",
      "rank": 82
    },
    {
      "seniority": 2201,
      "name": "Jake Smith",
      "rank": 83
    },
    {
      "seniority": 2216,
      "name": "Justin Ludwig",
      "rank": 84
    },
    {
      "seniority": 2225,
      "name": "Erich Kunrath",
      "rank": 85
    },
    {
      "seniority": 2227,
      "name": "Kirk Dalebroux",
      "rank": 86
    },
    {
      "seniority": 2242,
      "name": "Miguel N. Van Hoof",
      "rank": 87
    },
    {
      "seniority": 2252,
      "name": "Christopher M. Tuite",
      "rank": 88
    },
    {
      "seniority": 2254,
      "name": "Mark E. Whitesell",
      "rank": 89
    },
    {
      "seniority": 2256,
      "name": "John D. Peterson",
      "rank": 90
    },
    {
      "seniority": 2260,
      "name": "Brice S. Bowden",
      "rank": 91
    },
    {
      "seniority": 2263,
      "name": "Andrew R. Mosbrucker",
      "rank": 92
    },
    {
      "seniority": 2265,
      "name": "Gerald T. Wallace",
      "rank": 93
    },
    {
      "seniority": 2268,
      "name": "Jason P. Atterbury",
      "rank": 94
    },
    {
      "seniority": 2269,
      "name": "Kyle D. Kupers",
      "rank": 95
    },
    {
      "seniority": 2271,
      "name": "Ryan W. Geser",
      "rank": 96
    },
    {
      "seniority": 2274,
      "name": "Emily E. Brand",
      "rank": 97
    },
    {
      "seniority": 2286,
      "name": "Joshua D. Baresh",
      "rank": 98
    },
    {
      "seniority": 2309,
      "name": "Chadler W. Nieman",
      "rank": 99
    },
    {
      "seniority": 2311,
      "name": "Monica R. Matthews",
      "rank": 100
    },
    {
      "seniority": 2312,
      "name": "Christopher M. Cimino",
      "rank": 101
    },
    {
      "seniority": 2316,
      "name": "Navneil N. Singh",
      "rank": 102
    },
    {
      "seniority": 2320,
      "name": "Jorge L. Quintero",
      "rank": 103
    },
    {
      "seniority": 2326,
      "name": "Zachary W. Darrow",
      "rank": 104
    },
    {
      "seniority": 2327,
      "name": "Kyle K. Souders",
      "rank": 105
    },
    {
      "seniority": 2329,
      "name": "David K. Twombly",
      "rank": 106
    },
    {
      "seniority": 2355,
      "name": "David A. Sutherland",
      "rank": 107
    },
    {
      "seniority": 2359,
      "name": "Austin M. Duckett",
      "rank": 108
    },
    {
      "seniority": 2363,
      "name": "Joseph A. Milazzo",
      "rank": 109
    },
    {
      "seniority": 2374,
      "name": "Jeffrey A. Stevens",
      "rank": 110
    },
    {
      "seniority": 2379,
      "name": "Sarah O. Fritts",
      "rank": 111
    },
    {
      "seniority": 2382,
      "name": "Jeffrey M. Lamont",
      "rank": 112
    },
    {
      "seniority": 2387,
      "name": "Aaron W. Hommerding",
      "rank": 113
    },
    {
      "seniority": 2391,
      "name": "Brein Y. Tabachnick",
      "rank": 114
    },
    {
      "seniority": 2396,
      "name": "Marie A. Heckman",
      "rank": 115
    },
    {
      "seniority": 2405,
      "name": "Douglas M. Orwick",
      "rank": 116
    },
    {
      "seniority": 2413,
      "name": "Garrett J. Schmidt",
      "rank": 117
    },
    {
      "seniority": 2418,
      "name": "Richard C. Shupe",
      "rank": 118
    },
    {
      "seniority": 2422,
      "name": "Christopher A. Wright",
      "rank": 119
    },
    {
      "seniority": 2423,
      "name": "James R. Boughen",
      "rank": 120
    },
    {
      "seniority": 2424,
      "name": "Jeremy W. Smith",
      "rank": 121
    },
    {
      "seniority": 2428,
      "name": "Jason J. Fitch",
      "rank": 122
    },
    {
      "seniority": 2430,
      "name": "Tanner R. Mainero",
      "rank": 123
    },
    {
      "seniority": 2432,
      "name": "Christopher T. Garry",
      "rank": 124
    },
    {
      "seniority": 2434,
      "name": "Peter W. Simmons",
      "rank": 125
    },
    {
      "seniority": 2437,
      "name": "Jan D. Boersma",
      "rank": 126
    },
    {
      "seniority": 2449,
      "name": "Dhawal A. Patel",
      "rank": 127
    },
    {
      "seniority": 2450,
      "name": "Michael P. Kindsvater",
      "rank": 128
    },
    {
      "seniority": 2457,
      "name": "Anatoliy Kobylnik",
      "rank": 129
    },
    {
      "seniority": 2463,
      "name": "David F. Lemons",
      "rank": 130
    },
    {
      "seniority": 2477,
      "name": "Erik Gustav J. Malmberg",
      "rank": 131
    },
    {
      "seniority": 2479,
      "name": "Alexander R. Hall",
      "rank": 132
    },
    {
      "seniority": 2493,
      "name": "Jesse D. Buckwalter",
      "rank": 133
    },
    {
      "seniority": 2497,
      "name": "Eli T. Imhoff",
      "rank": 134
    },
    {
      "seniority": 2507,
      "name": "Eric W. Kemnitzer",
      "rank": 135
    },
    {
      "seniority": 2529,
      "name": "Chase J. Neuenschwander",
      "rank": 136
    },
    {
      "seniority": 2534,
      "name": "Mark B. Armstrong",
      "rank": 137
    },
    {
      "seniority": 2540,
      "name": "Monte A. Miller",
      "rank": 138
    },
    {
      "seniority": 2545,
      "name": "Dylan Helmer",
      "rank": 139
    },
    {
      "seniority": 2547,
      "name": "Jason Eichem",
      "rank": 140
    },
    {
      "seniority": 2548,
      "name": "Robert W. Foster",
      "rank": 141
    },
    {
      "seniority": 2550,
      "name": "Eric D. Anderson",
      "rank": 142
    },
    {
      "seniority": 2551,
      "name": "Loel K. Poulsen",
      "rank": 143
    },
    {
      "seniority": 2554,
      "name": "Joseph M. Chatterley",
      "rank": 144
    },
    {
      "seniority": 2560,
      "name": "Sean M. Hast",
      "rank": 145
    },
    {
      "seniority": 2573,
      "name": "Michael J. Abel",
      "rank": 146
    },
    {
      "seniority": 2597,
      "name": "Gregory A. Peterson",
      "rank": 147
    },
    {
      "seniority": 2603,
      "name": "Jaythan T. Williams",
      "rank": 148
    },
    {
      "seniority": 2607,
      "name": "Brett T. Hanson",
      "rank": 149
    },
    {
      "seniority": 2614,
      "name": "Alexander J. Lisandrelli",
      "rank": 150
    },
    {
      "seniority": 2621,
      "name": "Gage H. Geist",
      "rank": 151
    },
    {
      "seniority": 2627,
      "name": "Gregory D. Field",
      "rank": 152
    },
    {
      "seniority": 2634,
      "name": "Nathan T. Kemp",
      "rank": 153
    },
    {
      "seniority": 2652,
      "name": "Stefan P. Berry",
      "rank": 154
    },
    {
      "seniority": 2675,
      "name": "Darrel F. Carter, JR",
      "rank": 155
    },
    {
      "seniority": 2678,
      "name": "Carlos A. Valdez",
      "rank": 156
    },
    {
      "seniority": 2687,
      "name": "Zennon McNeill",
      "rank": 157
    },
    {
      "seniority": 2690,
      "name": "Bryce D. Kelly",
      "rank": 158
    },
    {
      "seniority": 2692,
      "name": "Jordan C. Quiogue",
      "rank": 159
    },
    {
      "seniority": 2693,
      "name": "Peter A. Dalton",
      "rank": 160
    },
    {
      "seniority": 2696,
      "name": "Megan L. Roadifer",
      "rank": 161
    },
    {
      "seniority": 2699,
      "name": "John C. Kleeh, III",
      "rank": 162
    },
    {
      "seniority": 2705,
      "name": "Carlos S. Meza",
      "rank": 163
    },
    {
      "seniority": 2716,
      "name": "Nathan Gavin",
      "rank": 164
    },
    {
      "seniority": 2717,
      "name": "Alexander Camponovo",
      "rank": 165
    },
    {
      "seniority": 2723,
      "name": "Keith A. Wilson",
      "rank": 166
    },
    {
      "seniority": 2724,
      "name": "Seth E. Johnson",
      "rank": 167
    },
    {
      "seniority": 2725,
      "name": "Randall L. Cox",
      "rank": 168
    },
    {
      "seniority": 2740,
      "name": "Bryan  . Ruwaldt",
      "rank": 169
    },
    {
      "seniority": 2750,
      "name": "Kraig M. Schell",
      "rank": 170
    },
    {
      "seniority": 2752,
      "name": "Joshua F. Griffith",
      "rank": 171
    },
    {
      "seniority": 2763,
      "name": "Devin D. Amico",
      "rank": 172
    },
    {
      "seniority": 2764,
      "name": "Eric S. Latimer",
      "rank": 173
    },
    {
      "seniority": 2781,
      "name": "Kevin K. Morita",
      "rank": 174
    },
    {
      "seniority": 2796,
      "name": "Jonathan D. Finklea",
      "rank": 175
    },
    {
      "seniority": 2801,
      "name": "Joshua E. Taylor",
      "rank": 176
    },
    {
      "seniority": 2807,
      "name": "Tessa R. Diaz",
      "rank": 177
    },
    {
      "seniority": 2812,
      "name": "Zachary D. Johnson",
      "rank": 178
    },
    {
      "seniority": 2823,
      "name": "Rosario F. Resta",
      "rank": 179
    },
    {
      "seniority": 2826,
      "name": "Loren M. Coulter",
      "rank": 180
    },
    {
      "seniority": 2827,
      "name": "William Hensick",
      "rank": 181
    },
    {
      "seniority": 2830,
      "name": "Kenneth B. Wagner",
      "rank": 182
    },
    {
      "seniority": 2832,
      "name": "Joel B. Owens",
      "rank": 183
    },
    {
      "seniority": 2846,
      "name": "Justin LK Sinclair",
      "rank": 184
    },
    {
      "seniority": 2863,
      "name": "Thomas J. Flaherty, Jr.",
      "rank": 185
    },
    {
      "seniority": 2864,
      "name": "Andrew M. Russ",
      "rank": 186
    },
    {
      "seniority": 2870,
      "name": "Alec M. Wheeler",
      "rank": 187
    },
    {
      "seniority": 2874,
      "name": "Detta R. Downs",
      "rank": 188
    },
    {
      "seniority": 2878,
      "name": "Alex J. Hoover",
      "rank": 189
    },
    {
      "seniority": 2892,
      "name": "Sean L. Culligan",
      "rank": 190
    },
    {
      "seniority": 2895,
      "name": "Ashton M. Gassman",
      "rank": 191
    },
    {
      "seniority": 2908,
      "name": "Jonathan M. Downey",
      "rank": 192
    },
    {
      "seniority": 2912,
      "name": "Christopher E. Riehn",
      "rank": 193
    },
    {
      "seniority": 2913,
      "name": "Dustin D. Moon",
      "rank": 194
    },
    {
      "seniority": 2917,
      "name": "Cade Black",
      "rank": 195
    },
    {
      "seniority": 2919,
      "name": "Charles E. Rounds",
      "rank": 196
    },
    {
      "seniority": 2935,
      "name": "Crystal L. Vaughan",
      "rank": 197
    },
    {
      "seniority": 2953,
      "name": "Christopher A. Burkholder",
      "rank": 198
    },
    {
      "seniority": 2955,
      "name": "John B. Stogdill",
      "rank": 199
    },
    {
      "seniority": 2966,
      "name": "Simon MD Mines",
      "rank": 200
    },
    {
      "seniority": 2970,
      "name": "Robert C. Lindgren",
      "rank": 201
    },
    {
      "seniority": 2988,
      "name": "Christopher J. Craven",
      "rank": 202
    },
    {
      "seniority": 3015,
      "name": "Brenda CL Smith",
      "rank": 203
    },
    {
      "seniority": 3019,
      "name": "Richard T. Egan",
      "rank": 204
    },
    {
      "seniority": 3025,
      "name": "Nicholas A. Schwab",
      "rank": 205
    },
    {
      "seniority": 3029,
      "name": "Peter J. Muessle",
      "rank": 206
    },
    {
      "seniority": 3041,
      "name": "Matthew M. Lariviere",
      "rank": 207
    },
    {
      "seniority": 3083,
      "name": "Daniel S. Kuhlman",
      "rank": 208
    },
    {
      "seniority": 3086,
      "name": "Joash Gonsalves",
      "rank": 209
    },
    {
      "seniority": 3087,
      "name": "Mitchell Drake",
      "rank": 210
    },
    {
      "seniority": 3106,
      "name": "Casey Precourt",
      "rank": 211
    },
    {
      "seniority": 3120,
      "name": "Daniel L. Jackson",
      "rank": 212
    },
    {
      "seniority": 3132,
      "name": "Travis J. Lee",
      "rank": 213
    }
  ]
}